CHANGES.rst
MANIFEST.in
README.rst
setup.py
src/collective/__init__.py
src/collective.vdexvocabulary.egg-info/PKG-INFO
src/collective.vdexvocabulary.egg-info/SOURCES.txt
src/collective.vdexvocabulary.egg-info/dependency_links.txt
src/collective.vdexvocabulary.egg-info/entry_points.txt
src/collective.vdexvocabulary.egg-info/namespace_packages.txt
src/collective.vdexvocabulary.egg-info/not-zip-safe
src/collective.vdexvocabulary.egg-info/requires.txt
src/collective.vdexvocabulary.egg-info/top_level.txt
src/collective/vdexvocabulary/__init__.py
src/collective/vdexvocabulary/configure.zcml
src/collective/vdexvocabulary/languages.zcml
src/collective/vdexvocabulary/meta.py
src/collective/vdexvocabulary/meta.rst
src/collective/vdexvocabulary/meta.zcml
src/collective/vdexvocabulary/months.zcml
src/collective/vdexvocabulary/term.py
src/collective/vdexvocabulary/term.rst
src/collective/vdexvocabulary/tests.py
src/collective/vdexvocabulary/treevocabulary.py
src/collective/vdexvocabulary/treevocabulary.rst
src/collective/vdexvocabulary/vocabulary.py
src/collective/vdexvocabulary/vdex/iso2788_relations.vdex
src/collective/vdexvocabulary/vdex/iso5964_equivalences.vdex
src/collective/vdexvocabulary/vdex/languages.vdex
src/collective/vdexvocabulary/vdex/months.vdex
src/collective/vdexvocabulary/vdex/treetest.vdex