Metadata-Version: 1.1
Name: collective.vdexvocabulary
Version: 0.2.2
Summary: IMS VDEX Vocabularies as Zope Vocabulary
Home-page: http://github.com/collective/collective.vdexvocabulary
Author: Rok Garbas
Author-email: rok@garbas.si
License: GPL
Keywords: plone vdex zope vocabulary
Platform: UNKNOWN
Classifier: Framework :: Zope2
Classifier: Framework :: Zope2
Classifier: Framework :: Plone
Classifier: Programming Language :: Python
Classifier: Topic :: Software Development :: Libraries :: Python Modules
